{
    "type": "object",
    "properties": {
        "trevera.searchPage.showItemsDisplayOptions": {
            "group": "searchConfig",
            "type": "boolean",
            "subtab": "resultDisplayOptions",
            "title": "Show Result Display Options",
            "description": "Show Result Display Options",
            "default": true
        },
        "trevera.searchPage.showNumberPerPageSelector": {
            "group": "searchConfig",
            "type": "boolean",
            "subtab": "resultsPerPage",
            "title": "Show Number Per Page Selector",
            "description": "Show Number Per Page Selector",
            "default": true
        },
        "trevera.searchPage.showSortSelector": {
            "group": "searchConfig",
            "type": "boolean",
            "subtab": "resultSorting",
            "title": "Show Sort Selector",
            "description": "Show Sort Selector",
            "default": true
        },
        "trevera.searchPage.defaultPaginationSettings.showPaginationTop": {
            "group": "advancedSettings",
            "type": "boolean",
            "subtab": "pagination",
            "title": "Show Pagination at Top",
            "description": "show pagination at the top of the list",
            "default": true
        }
    }
}
